CHANGES.txt
LICENCE.txt
README.txt
setup.cfg
setup.py
w20e/__init__.py
w20e.pycms.egg-info/PKG-INFO
w20e.pycms.egg-info/SOURCES.txt
w20e.pycms.egg-info/dependency_links.txt
w20e.pycms.egg-info/entry_points.txt
w20e.pycms.egg-info/not-zip-safe
w20e.pycms.egg-info/paster_plugins.txt
w20e.pycms.egg-info/requires.txt
w20e.pycms.egg-info/top_level.txt
w20e/pycms/TODO
w20e/pycms/__init__.py
w20e/pycms/actions.py
w20e/pycms/bootstrap.zcml
w20e/pycms/bootstrap_resources.zcml
w20e/pycms/catalog.py
w20e/pycms/catalog.zcml
w20e/pycms/configure.zcml
w20e/pycms/ctypes.py
w20e/pycms/events.py
w20e/pycms/index.py
w20e/pycms/interfaces.py
w20e/pycms/json_adapters.py
w20e/pycms/macros.py
w20e/pycms/mailer.py
w20e/pycms/manage_resources.zcml
w20e/pycms/meta.zcml
w20e/pycms/metadirectives.py
w20e/pycms/migration.py
w20e/pycms/nature.py
w20e/pycms/pack.py
w20e/pycms/parser.py
w20e/pycms/public_resources.zcml
w20e/pycms/renderers.py
w20e/pycms/search.zcml
w20e/pycms/security.py
w20e/pycms/security.zcml
w20e/pycms/tempregister.py
w20e/pycms/tests.py
w20e/pycms/utilities.py
w20e/pycms/utils.py
w20e/pycms/version.txt
w20e/pycms/blocks/README
w20e/pycms/blocks/__init__.py
w20e/pycms/blocks/base.py
w20e/pycms/blocks/cards.py
w20e/pycms/blocks/columns.py
w20e/pycms/blocks/configure.zcml
w20e/pycms/blocks/ext_content.py
w20e/pycms/blocks/feed.py
w20e/pycms/blocks/flowh.py
w20e/pycms/blocks/flowv.py
w20e/pycms/blocks/grid.py
w20e/pycms/blocks/image.py
w20e/pycms/blocks/ref.py
w20e/pycms/blocks/registry.py
w20e/pycms/blocks/snippet.py
w20e/pycms/blocks/text.py
w20e/pycms/blocks/templates/card.pt
w20e/pycms/blocks/templates/cards.pt
w20e/pycms/blocks/templates/column.pt
w20e/pycms/blocks/templates/columns.pt
w20e/pycms/blocks/templates/ext_content.pt
w20e/pycms/blocks/templates/feed.pt
w20e/pycms/blocks/templates/flowh.pt
w20e/pycms/blocks/templates/flowv.pt
w20e/pycms/blocks/templates/grid.pt
w20e/pycms/blocks/templates/gridcell.pt
w20e/pycms/blocks/templates/gridrow.pt
w20e/pycms/blocks/templates/image.pt
w20e/pycms/blocks/templates/ref.pt
w20e/pycms/blocks/templates/snippet.pt
w20e/pycms/blocks/templates/text.pt
w20e/pycms/forms/file.xml
w20e/pycms/forms/folder.xml
w20e/pycms/forms/form.xml
w20e/pycms/forms/image.xml
w20e/pycms/forms/imagefolder.xml
