Metadata-Version: 1.1
Name: w20e.pycms
Version: 1.1.2b
Summary: Pyramid CMS
Home-page: https://github.com/wyldebeast-wunderliebe/w20e.pycms/
Author: D.A.Dokter, H.Bouma
Author-email: dokter@w20e.com, bouma@w20e.com
License: beer-ware
Keywords: cms pyramid
Platform: UNKNOWN
Classifier: Development Status :: 3 - Alpha
Classifier: Framework :: Pyramid
Classifier: Intended Audience :: Developers
Classifier: License :: Freely Distributable
Classifier: Programming Language :: Python
Classifier: Topic :: Internet :: WWW/HTTP :: Site Management
Classifier: Topic :: Software Development :: Libraries :: Application Frameworks
